pairrot/__init__.py
pairrot/hints.py
pairrot/solver.py
pairrot/utils.py
pairrot/vocab.py
pairrot_solver-0.0.1.dist-info/LICENSE
pairrot_solver-0.0.1.dist-info/METADATA
pairrot_solver-0.0.1.dist-info/WHEEL
pairrot_solver-0.0.1.dist-info/top_level.txt
pairrot_solver-0.0.1.dist-info/RECORD
