Metadata-Version: 2.1
Name: pairrot-solver
Version: 0.0.1
Summary: A Python library for solving 쌍근 puzzles with various strategies.
Author-email: Jaesu Han <gkswotn9753@gmail.com>
Maintainer-email: Jaesu Han <gkswotn9753@gmail.com>
License: MIT License
Project-URL: Homepage, https://github.com/Jaesu26/pairrot-solver
Keywords: pairrot,solver
Classifier: Development Status :: 3 - Alpha
Classifier: Intended Audience :: Developers
Classifier: License :: OSI Approved :: MIT License
Classifier: Operating System :: OS Independent
Classifier: Programming Language :: Python
Classifier: Programming Language :: Python :: 3 :: Only
Classifier: Programming Language :: Python :: 3.10
Classifier: Programming Language :: Python :: 3.11
Classifier: Programming Language :: Python :: 3.12
Classifier: Topic :: Software Development :: Libraries :: Python Modules
Requires-Python: >=3.10
License-File: LICENSE
Requires-Dist: numpy>=1.24.4
Requires-Dist: tqdm>=4.66.4
